LICENSE
MANIFEST.in
README.rst
setup.py
version.txt
EVM/EVM.py
EVM/MultipleEVM.py
EVM/__init__.py
EVM/test.py
EVM.egg-info/PKG-INFO
EVM.egg-info/SOURCES.txt
EVM.egg-info/dependency_links.txt
EVM.egg-info/requires.txt
EVM.egg-info/top_level.txt