Metadata-Version: 1.1
Name: EVM
Version: 0.1.1
Summary: The Extreme Value Machine
Home-page: http://bitbucket.org/vastlab/evm
Author: Manuel Gunther
Author-email: siebenkopf@googlemail.com
License: BSD
Platform: UNKNOWN
Classifier: Development Status :: 3 - Alpha
Classifier: Intended Audience :: Developers
Classifier: License :: OSI Approved :: BSD License
Classifier: Natural Language :: English
Classifier: Programming Language :: Python
Classifier: Programming Language :: Python :: 3
Classifier: Topic :: Software Development :: Libraries :: Python Modules
